iptools.py
mindpowered_iptools/IPTools.py
mindpowered_iptools/__init__.py
mindpowered_iptools-0.0.17.dist-info/LICENSE.txt
mindpowered_iptools-0.0.17.dist-info/METADATA
mindpowered_iptools-0.0.17.dist-info/WHEEL
mindpowered_iptools-0.0.17.dist-info/top_level.txt
mindpowered_iptools-0.0.17.dist-info/RECORD
