Metadata-Version: 2.1
Name: mindpowered-iptools
Version: 0.0.17
Summary: Tools for working with IP4/IP6 IP Addresses including IPv4, IPv6, CIDR, and Subnet Masks
Home-page: https://mindpowered.dev/
Author: Mind Powered Corporation
Author-email: support@mindpowered.dev
License: MIT
Platform: UNKNOWN
Classifier: Programming Language :: Python :: 3
Classifier: Operating System :: OS Independent
Classifier: License :: OSI Approved :: MIT License
Requires-Dist: mindpowered-maglev
